heatgraphy/__init__.py
heatgraphy/_api.py
heatgraphy/_deform.py
heatgraphy/base.py
heatgraphy/dataset.py
heatgraphy/dendrogram.py
heatgraphy/exceptions.py
heatgraphy/heatmap.py
heatgraphy/layers.py
heatgraphy/layout.py
heatgraphy/upset.py
heatgraphy/utils.py
heatgraphy/plotter/__init__.py
heatgraphy/plotter/_seaborn.py
heatgraphy/plotter/bar.py
heatgraphy/plotter/base.py
heatgraphy/plotter/mesh.py
heatgraphy/plotter/text.py
heatgraphy-0.2.1.dist-info/LICENSE
heatgraphy-0.2.1.dist-info/WHEEL
heatgraphy-0.2.1.dist-info/METADATA
heatgraphy-0.2.1.dist-info/RECORD
