Metadata-Version: 2.1
Name: heatgraphy
Version: 0.2.1
Summary: Create x-layout visualization
Author-email: Mr-Milk <yb97643@um.edu.mo>
Requires-Python: >=3.8
Classifier: License :: OSI Approved :: MIT License
Requires-Dist: numpy
Requires-Dist: pandas
Requires-Dist: matplotlib>=3.6
Requires-Dist: seaborn
Requires-Dist: scipy
Requires-Dist: legendkit
Requires-Dist: platformdirs
Requires-Dist: icecream ; extra == "dev"
Requires-Dist: python-hmr ; extra == "dev"
Requires-Dist: pytest ; extra == "dev"
Requires-Dist: scikit-learn ; extra == "dev"
Requires-Dist: sphinx ; extra == "dev"
Requires-Dist: numpydoc ; extra == "dev"
Requires-Dist: sphinx_design ; extra == "dev"
Requires-Dist: pydata-sphinx-theme ; extra == "dev"
Requires-Dist: sphinx-copybutton ; extra == "dev"
Project-URL: Home, https://github.com/Heatgraphy/heatgraphy
Provides-Extra: dev
